project_ryland/__init__.py
project_ryland/cli.py
project_ryland/llm_utils/__init__.py
project_ryland/llm_utils/llm_config.py
project_ryland/llm_utils/llm_generation_utils.py
project_ryland/templates/__init__.py
project_ryland/templates/quickstart.py
project_ryland/templates/standard_quickstart/__init__.py
project_ryland/templates/standard_quickstart/project_ryland_quickstart.ipynb
project_ryland/templates/standard_quickstart/synthetic_clinical_notes.csv
project_ryland/templates/standard_quickstart/llm_prompt_gallery/__init__.py
project_ryland/templates/standard_quickstart/llm_prompt_gallery/config_llm_prompts.yaml
project_ryland/templates/standard_quickstart/llm_prompt_gallery/example_prompt_1.txt
project_ryland/templates/standard_quickstart/llm_prompt_gallery/example_prompt_2.txt
project_ryland/templates/standard_quickstart/llm_prompt_gallery/example_prompt_2_with_variables.txt
project_ryland/templates/standard_quickstart/llm_prompt_gallery/keyword_mappings.py
project_ryland/templates/standard_quickstart/llm_prompt_gallery/prompt_structs.py
project_ryland-2.1.6.dist-info/entry_points.txt
project_ryland-2.1.6.dist-info/licenses/LICENSE
project_ryland-2.1.6.dist-info/WHEEL
project_ryland-2.1.6.dist-info/METADATA
project_ryland-2.1.6.dist-info/RECORD
