Metadata-Version: 2.4
Name: project_ryland
Version: 2.1.6
Summary: This project contains standardized tools to use LLMs in research studies for improving patient care.
Author-email: Justin Vinh <jvinh21@gmail.com>
Requires-Python: >=3.10
Classifier: Programming Language :: Python :: 3
License-File: LICENSE
Requires-Dist: pandas>=2.0
Requires-Dist: numpy>=1.26
Requires-Dist: matplotlib>=3.9
Requires-Dist: scikit-learn>=1.5
Requires-Dist: lifelines>=0.28
Requires-Dist: tqdm>=4.66
Requires-Dist: numexpr>=2.10.2
Requires-Dist: loguru>=0.7
Requires-Dist: orjson>=3.10
Requires-Dist: pyyaml>=6.0
Requires-Dist: environs>=9.5
Requires-Dist: openai>=1.43
Requires-Dist: azure-identity>=1.17
Requires-Dist: azure-core>=1.30
Requires-Dist: pydantic>=2.6
Requires-Dist: python-dateutil>=2.9
Requires-Dist: requests>=2.31
